Paper/Verilator/AXI-Stream/AXI_Stream.v
module AXIStreamSlave(
  input   clock,
  input   reset,
  input   io_S_AXIS_TVALID,
  input   io_S_AXIS_TLAST,
  output  io_S_AXIS_TREADY
);
  reg [1:0] mst_exec_state;
  reg [31:0] _RAND_0;
  wire  _T;
  reg [4:0] write_pointer;
  reg [31:0] _RAND_1;
  wire  _T_1;
  wire  axis_tready;
  wire  _T_2;
  reg  writes_done;
  reg [31:0] _RAND_2;
  wire  fifo_wren;
  wire [5:0] _T_5;
  wire [5:0] _GEN_4;
  wire  _GEN_5;
  wire  _T_6;
  wire  _T_7;
  wire  _GEN_6;
  wire [5:0] _GEN_7;
  assign _T = mst_exec_state == 2'h1;
  assign _T_1 = write_pointer <= 5'h8;
  assign axis_tready = _T & _T_1;
  assign _T_2 = mst_exec_state == 2'h0;
  assign fifo_wren = io_S_AXIS_TVALID & axis_tready;
  assign _T_5 = write_pointer + 5'h1;
  assign _GEN_4 = fifo_wren ? _T_5 : {{1'd0}, write_pointer};
  assign _GEN_5 = fifo_wren ? 1'h0 : writes_done;
  assign _T_6 = write_pointer == 5'h8;
  assign _T_7 = _T_6 | io_S_AXIS_TLAST;
  assign _GEN_6 = _T_7 | _GEN_5;
  assign _GEN_7 = _T_1 ? _GEN_4 : {{1'd0}, write_pointer};
  assign io_S_AXIS_TREADY = _T & _T_1;
`ifdef RANDOMIZE_GARBAGE_ASSIGN
`define RANDOMIZE
`endif
`ifdef RANDOMIZE_INVALID_ASSIGN
`define RANDOMIZE
`endif
`ifdef RANDOMIZE_REG_INIT
`define RANDOMIZE
`endif
`ifdef RANDOMIZE_MEM_INIT
`define RANDOMIZE
`endif
`ifndef RANDOM
`define RANDOM $random
`endif
`ifdef RANDOMIZE_MEM_INIT
  integer initvar;
`endif
`ifndef SYNTHESIS
initial begin
  `ifdef RANDOMIZE
    `ifdef INIT_RANDOM
      `INIT_RANDOM
    `endif
    `ifndef VERILATOR
      `ifdef RANDOMIZE_DELAY
        #`RANDOMIZE_DELAY begin end
      `else
        #0.002 begin end
      `endif
    `endif
  `ifdef RANDOMIZE_REG_INIT
  _RAND_0 = {1{`RANDOM}};
  mst_exec_state = _RAND_0[1:0];
  `endif // RANDOMIZE_REG_INIT
  `ifdef RANDOMIZE_REG_INIT
  _RAND_1 = {1{`RANDOM}};
  write_pointer = _RAND_1[4:0];
  `endif // RANDOMIZE_REG_INIT
  `ifdef RANDOMIZE_REG_INIT
  _RAND_2 = {1{`RANDOM}};
  writes_done = _RAND_2[0:0];
  `endif // RANDOMIZE_REG_INIT
  `endif // RANDOMIZE
end // initial
`endif // SYNTHESIS
  always @(posedge clock) begin
    if (reset) begin
      mst_exec_state <= 2'h0;
    end else if (_T_2) begin
      if (io_S_AXIS_TVALID) begin
        mst_exec_state <= 2'h1;
      end else begin
        mst_exec_state <= 2'h0;
      end
    end else if (_T) begin
      if (writes_done) begin
        mst_exec_state <= 2'h0;
      end else begin
        mst_exec_state <= 2'h1;
      end
    end
    if (reset) begin
      write_pointer <= 5'h0;
    end else begin
      write_pointer <= _GEN_7[4:0];
    end
    if (reset) begin
      writes_done <= 1'h0;
    end else if (_T_1) begin
      writes_done <= _GEN_6;
    end
  end
endmodule
module AXIStreamMaster(
  input   clock,
  input   reset,
  output  io_M_AXIS_TVALID,
  output  io_M_AXIS_TLAST,
  input   io_M_AXIS_TREADY
);
  reg  axis_tvalid_delay;
  reg [31:0] _RAND_0;
  reg  axis_tlast_delay;
  reg [31:0] _RAND_1;
  reg [1:0] mst_exec_state;
  reg [31:0] _RAND_2;
  wire  _T;
  wire  _T_1;
  reg [5:0] count;
  reg [31:0] _RAND_3;
  wire  _T_4;
  reg  tx_done;
  reg [31:0] _RAND_4;
  wire  _T_2;
  wire [6:0] _T_3;
  wire [6:0] _GEN_1;
  wire [6:0] _GEN_5;
  wire [6:0] _GEN_7;
  reg [4:0] read_pointer;
  reg [31:0] _RAND_5;
  wire  _T_6;
  wire  axis_tvalid;
  wire  axis_tlast;
  wire  _T_7;
  wire  tx_en;
  wire  _T_9;
  wire [5:0] _T_8;
  wire  _GEN_8;
  wire [5:0] _GEN_9;
  wire [5:0] _GEN_11;
  assign _T = mst_exec_state == 2'h0;
  assign _T_1 = mst_exec_state == 2'h1;
  assign _T_4 = mst_exec_state == 2'h2;
  assign _T_2 = count == 6'h1f;
  assign _T_3 = count + 6'h1;
  assign _GEN_1 = _T_2 ? {{1'd0}, count} : _T_3;
  assign _GEN_5 = _T_1 ? _GEN_1 : {{1'd0}, count};
  assign _GEN_7 = _T ? {{1'd0}, count} : _GEN_5;
  assign _T_6 = read_pointer < 5'h8;
  assign axis_tvalid = _T_4 & _T_6;
  assign axis_tlast = read_pointer == 5'h7;
  assign _T_7 = read_pointer <= 5'h7;
  assign tx_en = io_M_AXIS_TREADY & axis_tvalid;
  assign _T_9 = read_pointer == 5'h8;
  assign _T_8 = read_pointer + 5'h1;
  assign _GEN_8 = _T_9 | tx_done;
  assign _GEN_9 = tx_en ? _T_8 : {{1'd0}, read_pointer};
  assign _GEN_11 = _T_7 ? _GEN_9 : {{1'd0}, read_pointer};
  assign io_M_AXIS_TVALID = axis_tvalid_delay;
  assign io_M_AXIS_TLAST = axis_tlast_delay;
`ifdef RANDOMIZE_GARBAGE_ASSIGN
`define RANDOMIZE
`endif
`ifdef RANDOMIZE_INVALID_ASSIGN
`define RANDOMIZE
`endif
`ifdef RANDOMIZE_REG_INIT
`define RANDOMIZE
`endif
`ifdef RANDOMIZE_MEM_INIT
`define RANDOMIZE
`endif
`ifndef RANDOM
`define RANDOM $random
`endif
`ifdef RANDOMIZE_MEM_INIT
  integer initvar;
`endif
`ifndef SYNTHESIS
initial begin
  `ifdef RANDOMIZE
    `ifdef INIT_RANDOM
      `INIT_RANDOM
    `endif
    `ifndef VERILATOR
      `ifdef RANDOMIZE_DELAY
        #`RANDOMIZE_DELAY begin end
      `else
        #0.002 begin end
      `endif
    `endif
  `ifdef RANDOMIZE_REG_INIT
  _RAND_0 = {1{`RANDOM}};
  axis_tvalid_delay = _RAND_0[0:0];
  `endif // RANDOMIZE_REG_INIT
  `ifdef RANDOMIZE_REG_INIT
  _RAND_1 = {1{`RANDOM}};
  axis_tlast_delay = _RAND_1[0:0];
  `endif // RANDOMIZE_REG_INIT
  `ifdef RANDOMIZE_REG_INIT
  _RAND_2 = {1{`RANDOM}};
  mst_exec_state = _RAND_2[1:0];
  `endif // RANDOMIZE_REG_INIT
  `ifdef RANDOMIZE_REG_INIT
  _RAND_3 = {1{`RANDOM}};
  count = _RAND_3[5:0];
  `endif // RANDOMIZE_REG_INIT
  `ifdef RANDOMIZE_REG_INIT
  _RAND_4 = {1{`RANDOM}};
  tx_done = _RAND_4[0:0];
  `endif // RANDOMIZE_REG_INIT
  `ifdef RANDOMIZE_REG_INIT
  _RAND_5 = {1{`RANDOM}};
  read_pointer = _RAND_5[4:0];
  `endif // RANDOMIZE_REG_INIT
  `endif // RANDOMIZE
end // initial
`endif // SYNTHESIS
  always @(posedge clock) begin
    if (reset) begin
      axis_tvalid_delay <= 1'h0;
    end else begin
      axis_tvalid_delay <= axis_tvalid;
    end
    if (reset) begin
      axis_tlast_delay <= 1'h0;
    end else begin
      axis_tlast_delay <= axis_tlast;
    end
    if (reset) begin
      mst_exec_state <= 2'h0;
    end else if (_T) begin
      mst_exec_state <= 2'h1;
    end else if (_T_1) begin
      if (_T_2) begin
        mst_exec_state <= 2'h2;
      end else begin
        mst_exec_state <= 2'h1;
      end
    end else if (_T_4) begin
      if (tx_done) begin
        mst_exec_state <= 2'h0;
      end else begin
        mst_exec_state <= 2'h2;
      end
    end
    if (reset) begin
      count <= 6'h0;
    end else begin
      count <= _GEN_7[5:0];
    end
    if (reset) begin
      tx_done <= 1'h0;
    end else if (_T_7) begin
      if (tx_en) begin
        tx_done <= 1'h0;
      end else begin
        tx_done <= _GEN_8;
      end
    end
    if (reset) begin
      read_pointer <= 5'h0;
    end else begin
      read_pointer <= _GEN_11[4:0];
    end
  end
endmodule
module AXI_Stream(
  input   clock,
  input   reset,
  output  io_AXIS_TVALID
);
  wire  slave_clock;
  wire  slave_reset;
  wire  slave_io_S_AXIS_TVALID;
  wire  slave_io_S_AXIS_TLAST;
  wire  slave_io_S_AXIS_TREADY;
  wire  master_clock;
  wire  master_reset;
  wire  master_io_M_AXIS_TVALID;
  wire  master_io_M_AXIS_TLAST;
  wire  master_io_M_AXIS_TREADY;
  AXIStreamSlave slave (
    .clock(slave_clock),
    .reset(slave_reset),
    .io_S_AXIS_TVALID(slave_io_S_AXIS_TVALID),
    .io_S_AXIS_TLAST(slave_io_S_AXIS_TLAST),
    .io_S_AXIS_TREADY(slave_io_S_AXIS_TREADY)
  );
  AXIStreamMaster master (
    .clock(master_clock),
    .reset(master_reset),
    .io_M_AXIS_TVALID(master_io_M_AXIS_TVALID),
    .io_M_AXIS_TLAST(master_io_M_AXIS_TLAST),
    .io_M_AXIS_TREADY(master_io_M_AXIS_TREADY)
  );
  assign io_AXIS_TVALID = master_io_M_AXIS_TVALID;
  assign slave_clock = clock;
  assign slave_reset = reset;
  assign slave_io_S_AXIS_TVALID = master_io_M_AXIS_TVALID;
  assign slave_io_S_AXIS_TLAST = master_io_M_AXIS_TLAST;
  assign master_clock = clock;
  assign master_reset = reset;
  assign master_io_M_AXIS_TREADY = slave_io_S_AXIS_TREADY;
endmodule

Paper/multi-level/Treadle/PT-Treadle/AXI-Stream/AXI_Stream.vcd
$version Generated by VerilatedVcd $end
$date Fri Sep  4 20:53:36 2020
 $end
$timescale   1ns $end

 $scope module TOP $end
  $var wire  1 1 clock $end
  $var wire  1 3 io_AXIS_TVALID $end
  $var wire  1 2 reset $end
  $scope module AXI_Stream $end
   $var wire  1 1 clock $end
   $var wire  1 3 io_AXIS_TVALID $end
   $var wire  1 1 master_clock $end
   $var wire  1 ' master_io_M_AXIS_TLAST $end
   $var wire  1 ( master_io_M_AXIS_TREADY $end
   $var wire  1 & master_io_M_AXIS_TVALID $end
   $var wire  1 2 master_reset $end
   $var wire  1 2 reset $end
   $var wire  1 1 slave_clock $end
   $var wire  1 ' slave_io_S_AXIS_TLAST $end
   $var wire  1 ( slave_io_S_AXIS_TREADY $end
   $var wire  1 & slave_io_S_AXIS_TVALID $end
   $var wire  1 2 slave_reset $end
   $scope module master $end
    $var wire  1 0 axis_tlast $end
    $var wire  1 ' axis_tlast_delay $end
    $var wire  1 $ axis_tvalid $end
    $var wire  1 & axis_tvalid_delay $end
    $var wire  1 1 clock $end
    $var wire  6 - count [5:0] $end
    $var wire  1 ' io_M_AXIS_TLAST $end
    $var wire  1 ( io_M_AXIS_TREADY $end
    $var wire  1 & io_M_AXIS_TVALID $end
    $var wire  2 , mst_exec_state [1:0] $end
    $var wire  5 / read_pointer [4:0] $end
    $var wire  1 2 reset $end
    $var wire  1 . tx_done $end
    $var wire  1 % tx_en $end
   $upscope $end
   $scope module slave $end
    $var wire  1 ( axis_tready $end
    $var wire  1 1 clock $end
    $var wire  1 # fifo_wren $end
    $var wire  1 ' io_S_AXIS_TLAST $end
    $var wire  1 ( io_S_AXIS_TREADY $end
    $var wire  1 & io_S_AXIS_TVALID $end
    $var wire  2 ) mst_exec_state [1:0] $end
    $var wire  1 2 reset $end
    $var wire  5 * write_pointer [4:0] $end
    $var wire  1 + writes_done $end
   $upscope $end
  $upscope $end
 $upscope $end
$enddefinitions $end


#0
0#
0$
0%
0&
0'
0(
b00 )
b00000 *
0+
b00 ,
b000000 -
0.
b00000 /
00
01
02
03
#1
b01 ,
11
#2
01
#3
b000001 -
11
#4
01
#5
b000010 -
11
#6
01
#7
b000011 -
11
#8
01
#9
b000100 -
11
#10
01
#11
b000101 -
11
#12
01
#13
b000110 -
11
#14
01
#15
b000111 -
11
#16
01
#17
b001000 -
11
#18
01
#19
b001001 -
11
#20
01
#21
b001010 -
11
#22
01
#23
b001011 -
11
#24
01
#25
b001100 -
11
#26
01
#27
b001101 -
11
#28
01
#29
b001110 -
11
#30
01
#31
b001111 -
11
#32
01
#33
b010000 -
11
#34
01
#35
b010001 -
11
#36
01
#37
b010010 -
11
#38
01
#39
b010011 -
11
#40
01
#41
b010100 -
11
#42
01
#43
b010101 -
11
#44
01
#45
b010110 -
11
#46
01
#47
b010111 -
11
#48
01
#49
b011000 -
11
#50
01
#51
b011001 -
11
#52
01
#53
b011010 -
11
#54
01
#55
b011011 -
11
#56
01
#57
b011100 -
11
#58
01
#59
b011101 -
11
#60
01
#61
b011110 -
11
#62
01
#63
b011111 -
11
#64
01
#65
1$
b10 ,
11
#66
01
#67
1&
11
13
#68
01
#69
1#
1%
1(
b01 )
11
#70
01
#71
b00001 *
b00001 /
11
#72
01
#73
b00010 *
b00010 /
11
#74
01
#75
b00011 *
b00011 /
11
#76
01
#77
b00100 *
b00100 /
11
#78
01
#79
b00101 *
b00101 /
11
#80
01
#81
b00110 *
b00110 /
11
#82
01
#83
b00111 *
b00111 /
10
11
#84
01
#85
0$
0%
1'
b01000 *
b01000 /
00
11
#86
01
#87
0#
0&
0'
0(
b01001 *
1+
11
03
#88
01
#89
b00 )
11
